netbox_nas/__init__.py
netbox_nas/filtersets.py
netbox_nas/forms.py
netbox_nas/graphql.py
netbox_nas/models.py
netbox_nas/navigation.py
netbox_nas/search.py
netbox_nas/tables.py
netbox_nas/urls.py
netbox_nas/views.py
netbox_nas/api/__init__.py
netbox_nas/api/serializers.py
netbox_nas/api/urls.py
netbox_nas/api/views.py
netbox_nas/migrations/0001_initial.py
netbox_nas/migrations/__init__.py
netbox_nas/templates/netbox_nas/nascluster.html
netbox_nas/templates/netbox_nas/nasmount.html
netbox_nas/templates/netbox_nas/nasshare.html
netbox_nas/templates/netbox_nas/nasvolume.html
netbox_nas-1.0.4.dist-info/METADATA
netbox_nas-1.0.4.dist-info/WHEEL
netbox_nas-1.0.4.dist-info/top_level.txt
netbox_nas-1.0.4.dist-info/RECORD
