Metadata-Version: 2.1
Name: netbox-nas
Version: 1.0.4
Summary: Add NAS entities to NetBox
